alu/rtl/top.v
module alu #(parameter N = 32) (
	input wire [N - 1: 0] a,
	input wire [N - 1: 0] b,
	input wire [3:0] ctrl,
	output reg [N - 1: 0] result,
	output reg zero,
	output reg negative,
	output reg overflow,
	output reg carry
);

reg [N : 0] temp;

initial begin
	if (N < 4 | N > 32) begin
		$display("-----------------------------------------------------------------------------------------------------------");
		$display("-------------------------------------------N OUT OF RANGE 3 < N < 32---------------------------------------");
		$display("-----------------------------------------------------------------------------------------------------------");
	end
end

always @(*) begin
	zero = 1'b0;
	negative = 1'b0;
	overflow = 1'b0;
	carry = 1'b0;
	result = {N{1'b0}};

	case(ctrl)
		4'b0000: begin
			temp = {1'b0, a} + {1'b0, b};
			result = temp[N - 1: 0];
			carry = temp[N];
			overflow = ((~a[N - 1] & ~b[N - 1] & result[N - 1]) | (a[N - 1] & b[N - 1] & ~result[N - 1]));
		end
		4'b0001: begin
			temp =  a + {~b + 1'b1};
			result = temp[N - 1: 0];
			carry = ~temp[N];
			overflow = ((a[N - 1] & ~b[N - 1] & ~result[N - 1]) | (~a[N - 1] & b[N - 1] & result[N - 1]));
		end
		4'b0010: begin
			result = a & b;
			carry = 1'b0;
			overflow = 1'b0;
		end
		4'b0011: begin
			result = a | b;
			carry = 1'b0;
			overflow = 1'b0;
		end
		4'b0100: begin
			result = a ^ b;
			carry = 1'b0;
			overflow = 1'b0;
		end
		4'b0101: begin
			result = ~a;
			carry = 1'b0;
			overflow = 1'b0;
		end
		4'b0110: begin
			result = a << b[3:0];
			carry = 1'b0;
			overflow = 1'b0;
		end
		4'b0111: begin
			result = a >> b[3 : 0];
			carry = 1'b0;
			overflow = 1'b0;
		end
		4'b1000: begin
			result = $signed(a) >>> b[3 : 0];
			carry = 1'b0;
			overflow = 1'b0;
		end
		4'b1001: begin
			result = (a == b) ? {N{1'b1}} : {N{1'b0}};
			carry = 1'b0;
			overflow = 1'b0;
		end
		4'b1010: begin
			result = (a < b) ? {N{1'b1}} : {N{1'b0}};
			carry = 1'b0;
			overflow = 1'b0;
		end
		4'b1011: begin
			result = (a > b) ? {N{1'b1}} : {N{1'b0}};
			carry = 1'b0;
			overflow = 1'b0;
		end
		4'b1100: begin
			result = a[N/2 : 0] * b[N/2 : 0];
			carry = 1'b0;
			overflow = 1'b0;
		end
		4'b1101: begin
			result = (b != 0) ? a/b : {N{1'b0}};
			carry = 1'b0;
			overflow = 1'b0;
		end
		4'b1110: begin
			result = (b != 0) ? a%b : {N{1'b0}};
			carry = 1'b0;
			overflow = 1'b0;
		end
		default: begin
			result = {N{1'b0}};
			carry = 1'b0;
			overflow = 1'b0;
		end
	endcase
	zero = (result == {N{1'b0}}) ? 1'b1 : 1'b0;
	negative = (ctrl == 4'b0001) ? (a[N - 1] ^ b[N - 1] ? ~result[N - 1] : result[N - 1]) : result[N - 1];
end
endmodule

alu/tb/test_bench.v
`timescale 1ns/1ps
module test_bench;
	parameter N = 32;

	reg [N - 1: 0] a;
	reg [N - 1: 0] b;
	reg [3:0] ctrl;

	wire [N - 1: 0] result;
	wire zero;
	wire negative;
	wire overflow;
	wire carry;

	alu #(N) dut(
		.a(a),
		.b(b),
		.ctrl(ctrl),
		.result(result),
		.zero(zero),	
		.negative(negative),
		.overflow(overflow),
		.carry(carry)
	);

	task verify;
		input [N - 1 : 0] exp_result;
		input exp_zero, exp_negative, exp_overflow, exp_carry;
		begin
			#5;
			$display("At time: %t, a = %b, b = %b, ctrl = 4'b%b", $time, a, b, ctrl);
			if (result !== exp_result || zero !== exp_zero || negative !== exp_negative || overflow !== exp_overflow || carry !== exp_carry) begin
				$display("-------------------------------------------------------------------------------------------------------------------------------------");
				$display("-------------------------------------------RUN TESTBENCH AT TESTCASE: FAILED---------------------------------------------------------");
				$display("Expedted: exp_result: %b, exp_zero: %b, exp_negative: %b, exp_overflow: %b, exp_carry:%b", exp_result, exp_zero, exp_negative, exp_overflow, exp_carry);
				$display("Got: result: %b, zero = %b, negative: %b, overflow: %b, carry: %b", result, zero, negative, overflow, carry);
				$display("-------------------------------------------------------------------------------------------------------------------------------------");
			end else begin
				$display("-------------------------------------------------------------------------------------------------------------------------------------");
				$display("------------------------------------------RUN TESTBENCH AT TESTCASE: PASSED----------------------------------------------------------");
				$display("Expected: exp_result: %b, exp_zero: %b, exp_negative: %b, exp_overflow: %b, exp_carry: %b", exp_result, exp_zero, exp_negative, exp_overflow, exp_carry);
				$display("Got: result: %b, zero: %b, negative: %b, overflow: %b, carry: %b", result, zero, negative, overflow, carry);
				$display("-------------------------------------------------------------------------------------------------------------------------------------");
			end
		end
	endtask

	initial begin
		$dumpfile("test_bench.vcd");
		$dumpvars(0, test_bench);

		$display("-------------------------------------------------------------------------------------------------------------------------------------");
		$display("----------------------------------------------- TESTBENCH FOR ALU N BIT--------------------------------------------------------------");
		$display("-------------------------------------------------------------------------------------------------------------------------------------");
		
		// Test case 1: add operation
		ctrl = 4'b0000;
		a = 32'h00000010;
		b = 32'h00000020;
		#20;
		verify(32'h00000030, 0, 0, 0, 0);

		// Test case 2: Add operation
		ctrl = 4'b0000;
		a = 32'h80000000;
		b = 32'h80000000;
		#20;
		verify(32'h00000000,1, 0, 1, 1);

		// Test case 3: Subtract operation
		ctrl = 4'b0001;
		a = 32'h00000030;
		b = 32'h00000010;
		#20;
		verify(32'h00000020, 0, 0, 0, 0);

		// Test case 4: Subtract operation
		ctrl = 4'b0001;
		a = 32'h80000000;
		b = 32'h7fffffff;
		#20;
		verify(32'h00000001, 0, 1, 1, 0);

		// Test case 5: And operation
		ctrl = 4'b0010;
		a = 32'haaaaaaaa;
		b = 32'h55555555;
		#20;
		verify(32'h00000000, 1, 0, 0, 0);
		
		// Test case 6: And operation
		ctrl = 4'b0010;
		a = 32'hf0dae34f;
		b = 32'h7dafacbc;
		#20;
		verify(32'h708aa00c, 0, 0, 0, 0);

		// Test case 7: OR operation
		ctrl = 4'b0011;
		a = 32'haaaaaaaa;
		b = 32'h55555555;
		#20;
		verify(32'hffffffff, 0, 1, 0, 0);

		// Test case 8: OR operation
		ctrl = 4'b0011;
		a = 32'hcccccccc;
		b = 32'h00000001;
		#20;
		verify(32'hcccccccd, 0, 1, 0, 0);

		// Test case 9: XOR operation
		ctrl = 4'b0100;
		a = 32'haaaaaaaa;
		b = 32'h55555555;
		#20;
		verify(32'hffffffff, 0, 1, 0, 0);

		// Test case 10: XOR operation
		ctrl = 4'b0100;
		a = 32'h10101010;
		b = 32'h10101010;
		#20;
		verify(32'h00000000, 1, 0, 0, 0);

		// Test case 11: NOT operation
		ctrl = 4'b0101;
		a = 32'hffffffff;
		#20;
		verify(32'h00000000, 1, 0, 0, 0);
		
		// Test case 12: SHILF LEFT operation
		ctrl = 4'b0110;
		a = 32'h12345678;
		b = 32'h00000008;
		#20;
		verify(32'h34567800, 0, 0, 0, 0);

		// Test case 13: SHIFT LEFT operation
		ctrl = 4'b0110;
		a = 32'habcdef45;
		b = 32'h15789004;
		#20;
		verify(32'hbcdef450, 0, 1, 0, 0);

		// Test case 14: SHIFT RIGHT operation
		ctrl = 4'b0111;
		a = 32'h15975312;
		b = 32'habefd044;
		#20;
		verify(32'h01597531, 0, 0, 0, 0);

		// Test case 15: SHIFT  RIGHT operation
		ctrl = 4'b0111;
		a = 32'hbadefc45;
		b = 32'h14895608;
		#20;
		verify(32'h00badefc, 0, 0, 0, 0);

		//Test case 16: ARITHMETIC SHIFT RIGHT operation
		ctrl = 4'b1000;
		a = 32'h8fffffff;
		b = 32'h12345674;
		#20;
		verify(32'hf8ffffff, 0, 1, 0, 0);

		// Test case 17: ARITHMETIC SHHIFT RIGHT operation
		ctrl = 4'b1000;
		a = 32'h7abcdeff;
		b = 32'h15236808;
		#20;
		verify(32'h007abcde, 0, 0, 0, 0);

		// Test case 18: EQUALY operation
		ctrl = 4'b1001;
		a = 32'h23456789;
		b = 32'h12345678;
		#20;
		verify(32'h00000000, 1, 0, 0, 0);

		//Test case 19: EQUALY operation
		ctrl = 4'b1001;
		a = 32'habcdefaa;
		b = 32'habcdefaa;
		#20;
		verify(32'hffffffff, 0, 1, 0, 0);
		
		// Test case 20: LESS THAN operation
		ctrl = 4'b1010;
		a = 32'h7fffffff;
		b = 32'h8fffffff;
		#20;
		verify(32'hffffffff, 0, 1, 0, 0);
		
		// Test case 21: LESS THAN operation 
		ctrl = 4'b1010;
		a = 32'h3fffffff;
		b = 32'h0fffffff;
		#20;
		verify(32'h00000000, 1, 0, 0, 0);	

		// Test case 22: GREATER THAN operation
		ctrl = 4'b1011;
		a = 32'h40021057;
		b = 32'h3fd4789d;
		#20;
		verify(32'hffffffff, 0, 1, 0, 0);

		// Test case 23: GREATER THAN operation
		ctrl = 4'b1011;
		a = 32'h7fffffff;
		b = 32'h8fffffff;
		#20;
		verify(32'h00000000, 1, 0, 0, 0);

		// Test case 24: Multiplication
		ctrl = 4'b1100;
		a = 32'h00001234;
		b = 32'h0000abcd;
		#20;
		verify(32'h0c374fa4, 0, 0, 0 ,0);

		// Test case 25: Multiplication
		ctrl = 4'b1100;
		a = 32'hff001478;
		b = 32'h12340ef7;
		#20;
		verify(32'h01324fc8, 0, 0, 0 ,0);

		// Test case 26: Division
		ctrl = 4'b1101;
		a = 32'habcdef85;
		b = 32'h12345678;
		#20;
		verify(32'h00000009, 0, 0, 0, 0);

		// test case 27: Division
		ctrl = 4'b1101;
		a = 32'h14253679;
		b = 32'h00000000;
		#20;
		verify(32'h00000000, 1, 0, 0, 0);

		// Test case 28: Modulus
		ctrl = 4'b1110;
		a = 32'h14725836;
		b = 32'h00abfecd;
		#20;
		verify(32'h004a7c30, 0, 0, 0, 0);

		// Test case 29: Modulus
		ctrl = 4'b1110;
		a = 32'h15768943;
		b = 32'h00000000;;
		#20;
		verify(32'h00000000, 1, 0, 0, 0);

		// Default case
		ctrl = 4'b1111;
		a = 32'ha5b782ff;
		b = 32'h10000000;
		#20;
		verify(32'h00000000, 1, 0, 0, 0);

		#100;
		$finish;
	end
endmodule

alu/sim/test_bench.vcd
$date
	Wed Jan  1 22:01:45 2025
$end
$version
	Icarus Verilog
$end
$timescale
	1ps
$end
$scope module test_bench $end
$var wire 1 ! zero $end
$var wire 32 " result [31:0] $end
$var wire 1 # overflow $end
$var wire 1 $ negative $end
$var wire 1 % carry $end
$var parameter 32 & N $end
$var reg 32 ' a [31:0] $end
$var reg 32 ( b [31:0] $end
$var reg 4 ) ctrl [3:0] $end
$scope module dut $end
$var wire 32 * a [31:0] $end
$var wire 32 + b [31:0] $end
$var wire 4 , ctrl [3:0] $end
$var parameter 32 - N $end
$var reg 1 % carry $end
$var reg 1 $ negative $end
$var reg 1 # overflow $end
$var reg 32 . result [31:0] $end
$var reg 33 / temp [32:0] $end
$var reg 1 ! zero $end
$upscope $end
$scope task verify $end
$var reg 1 0 exp_carry $end
$var reg 1 1 exp_negative $end
$var reg 1 2 exp_overflow $end
$var reg 32 3 exp_result [31:0] $end
$var reg 1 4 exp_zero $end
$upscope $end
$upscope $end
$enddefinitions $end
$comment Show the parameter values. $end
$dumpall
b100000 -
b100000 &
$end
#0
$dumpvars
x4
bx 3
x2
x1
x0
b110000 /
b110000 .
b0 ,
b100000 +
b10000 *
b0 )
b100000 (
b10000 '
0%
0$
0#
b110000 "
0!
$end
#20000
00
02
01
04
b110000 3
#25000
1!
1#
1%
b100000000000000000000000000000000 /
b0 "
b0 .
b10000000000000000000000000000000 (
b10000000000000000000000000000000 +
b10000000000000000000000000000000 '
b10000000000000000000000000000000 *
#45000
10
12
14
b0 3
#50000
b100000 "
b100000 .
b100000000000000000000000000100000 /
0%
0#
0!
b10000 (
b10000 +
b110000 '
b110000 *
b1 )
b1 ,
#70000
00
02
04
b100000 3
#75000
1$
1#
b100000000000000000000000000000001 /
b1 "
b1 .
b1111111111111111111111111111111 (
b1111111111111111111111111111111 +
b10000000000000000000000000000000 '
b10000000000000000000000000000000 *
#95000
12
11
b1 3
#100000
1!
b0 "
b0 .
0#
0$
b1010101010101010101010101010101 (
b1010101010101010101010101010101 +
b10101010101010101010101010101010 '
b10101010101010101010101010101010 *
b10 )
b10 ,
#120000
02
01
14
b0 3
#125000
b1110000100010101010000000001100 "
b1110000100010101010000000001100 .
0!
b1111101101011111010110010111100 (
b1111101101011111010110010111100 +
b11110000110110101110001101001111 '
b11110000110110101110001101001111 *
#145000
04
b1110000100010101010000000001100 3
#150000
1$
b11111111111111111111111111111111 "
b11111111111111111111111111111111 .
b1010101010101010101010101010101 (
b1010101010101010101010101010101 +
b10101010101010101010101010101010 '
b10101010101010101010101010101010 *
b11 )
b11 ,
#170000
11
b11111111111111111111111111111111 3
#175000
b11001100110011001100110011001101 "
b11001100110011001100110011001101 .
1$
b1 (
b1 +
b11001100110011001100110011001100 '
b11001100110011001100110011001100 *
#195000
b11001100110011001100110011001101 3
#200000
b11111111111111111111111111111111 "
b11111111111111111111111111111111 .
1$
b1010101010101010101010101010101 (
b1010101010101010101010101010101 +
b10101010101010101010101010101010 '
b10101010101010101010101010101010 *
b100 )
b100 ,
#220000
b11111111111111111111111111111111 3
#225000
1!
b0 "
b0 .
0$
b10000000100000001000000010000 (
b10000000100000001000000010000 +
b10000000100000001000000010000 '
b10000000100000001000000010000 *
#245000
01
14
b0 3
#250000
1!
b11111111111111111111111111111111 '
b11111111111111111111111111111111 *
b101 )
b101 ,
#275000
b110100010101100111100000000000 "
b110100010101100111100000000000 .
0!
b1000 (
b1000 +
b10010001101000101011001111000 '
b10010001101000101011001111000 *
b110 )
b110 ,
#295000
04
b110100010101100111100000000000 3
#300000
1$
b10111100110111101111010001010000 "
b10111100110111101111010001010000 .
b10101011110001001000000000100 (
b10101011110001001000000000100 +
b10101011110011011110111101000101 '
b10101011110011011110111101000101 *
#320000
11
b10111100110111101111010001010000 3
#325000
b1010110010111010100110001 "
b1010110010111010100110001 .
0$
b10101011111011111101000001000100 (
b10101011111011111101000001000100 +
b10101100101110101001100010010 '
b10101100101110101001100010010 *
b111 )
b111 ,
#345000
01
b1010110010111010100110001 3
#350000
b101110101101111011111100 "
b101110101101111011111100 .
b10100100010010101011000001000 (
b10100100010010101011000001000 +
b10111010110111101111110001000101 '
b10111010110111101111110001000101 *
#370000
b101110101101111011111100 3
#375000
1$
b11111000111111111111111111111111 "
b11111000111111111111111111111111 .
b10010001101000101011001110100 (
b10010001101000101011001110100 +
b10001111111111111111111111111111 '
b10001111111111111111111111111111 *
b1000 )
b1000 ,
#395000
11
b11111000111111111111111111111111 3
#400000
b11110101011110011011110 "
b11110101011110011011110 .
0$
b10101001000110110100000001000 (
b10101001000110110100000001000 +
b1111010101111001101111011111111 '
b1111010101111001101111011111111 *
#420000
01
b11110101011110011011110 3
#425000
1!
b0 "
b0 .
b10010001101000101011001111000 (
b10010001101000101011001111000 +
b100011010001010110011110001001 '
b100011010001010110011110001001 *
b1001 )
b1001 ,
#445000
14
b0 3
#450000
1$
b11111111111111111111111111111111 "
b11111111111111111111111111111111 .
0!
b10101011110011011110111110101010 (
b10101011110011011110111110101010 +
b10101011110011011110111110101010 '
b10101011110011011110111110101010 *
#470000
11
04
b11111111111111111111111111111111 3
#475000
b11111111111111111111111111111111 "
b11111111111111111111111111111111 .
1$
b10001111111111111111111111111111 (
b10001111111111111111111111111111 +
b1111111111111111111111111111111 '
b1111111111111111111111111111111 *
b1010 )
b1010 ,
#500000
1!
b0 "
b0 .
0$
b1111111111111111111111111111 (
b1111111111111111111111111111 +
b111111111111111111111111111111 '
b111111111111111111111111111111 *
#520000
01
14
b0 3
#525000
1$
b11111111111111111111111111111111 "
b11111111111111111111111111111111 .
0!
b111111110101000111100010011101 (
b111111110101000111100010011101 +
b1000000000000100001000001010111 '
b1000000000000100001000001010111 *
b1011 )
b1011 ,
#545000
11
04
b11111111111111111111111111111111 3
#550000
1!
b0 "
b0 .
0$
b10001111111111111111111111111111 (
b10001111111111111111111111111111 +
b1111111111111111111111111111111 '
b1111111111111111111111111111111 *
#570000
01
14
b0 3
#575000
b1100001101110100111110100100 "
b1100001101110100111110100100 .
0!
b1010101111001101 (
b1010101111001101 +
b1001000110100 '
b1001000110100 *
b1100 )
b1100 ,
#595000
04
b1100001101110100111110100100 3
#600000
b1001100100100111111001000 "
b1001100100100111111001000 .
b10010001101000000111011110111 (
b10010001101000000111011110111 +
b11111111000000000001010001111000 '
b11111111000000000001010001111000 *
#620000
b1001100100100111111001000 3
#625000
b1001 "
b1001 .
b10010001101000101011001111000 (
b10010001101000101011001111000 +
b10101011110011011110111110000101 '
b10101011110011011110111110000101 *
b1101 )
b1101 ,
#645000
b1001 3
#650000
1!
b0 "
b0 .
b0 (
b0 +
b10100001001010011011001111001 '
b10100001001010011011001111001 *
#670000
14
b0 3
#675000
b10010100111110000110000 "
b10010100111110000110000 .
0!
b101010111111111011001101 (
b101010111111111011001101 +
b10100011100100101100000110110 '
b10100011100100101100000110110 *
b1110 )
b1110 ,
#695000
04
b10010100111110000110000 3
#700000
1!
b0 "
b0 .
b0 (
b0 +
b10101011101101000100101000011 '
b10101011101101000100101000011 *
#720000
14
b0 3
#725000
1!
b10000000000000000000000000000 (
b10000000000000000000000000000 +
b10100101101101111000001011111111 '
b10100101101101111000001011111111 *
b1111 )
b1111 ,
